[{"item_name": "RAM-used", "value_max": "None", "value_avg": "None", "percentil": "None"}, {"item_name": "Used disk space on $1", "value_max": 2700.79, "value_avg": 2700.78, "percentil": 2565.75}, {"item_name": "Incoming network traffic on $1", "value_max": 49.14, "value_avg": 10.28, "percentil": 46.68}, {"item_name": "Outgoing network traffic on $1", "value_max": 18.3, "value_avg": 1.92, "percentil": 17.39}, {"item_name": "CPU Usage", "value_max": "None", "value_avg": "None", "percentil": "None"}, {"item_name": "iostat.sda", "value_max": "None", "value_avg": "None", "percentil": "None"}, {"item_name": "read.sda", "value_max": "None", "value_avg": "None", "percentil": "None"}, {"item_name": "write.sda", "value_max": "None", "value_avg": "None", "percentil": "None"}]